device_kit/__init__.py
device_kit/__main__.py
device_kit/adevice.py
device_kit/basedevice.py
device_kit/cdevice.py
device_kit/cdevice2.py
device_kit/device.py
device_kit/deviceset.py
device_kit/functions.py
device_kit/gdevice.py
device_kit/idevice.py
device_kit/idevice2.py
device_kit/mfdeviceset.py
device_kit/plots.py
device_kit/pvdevice.py
device_kit/run.py
device_kit/sdevice.py
device_kit/solve.py
device_kit/subbalanceddeviceset.py
device_kit/tdevice.py
device_kit/tworatiomfdeviceset.py
device_kit/utils.py
device_kit/windowdevice.py
device_kit/loaders/__init__.py
device_kit/loaders/builder_loader.py
device_kit/loaders/module_loader.py
device_kit/projection/__init__.py
device_kit/projection/projection.py
device_kit/sample_scenarios/__init__.py
device_kit/sample_scenarios/aircons_only_x10_scenario.py
device_kit/sample_scenarios/ev_charge_scenario.py
device_kit/sample_scenarios/iload_storage_supply.py
device_kit-1.0.10.dist-info/METADATA
device_kit-1.0.10.dist-info/WHEEL
device_kit-1.0.10.dist-info/top_level.txt
device_kit-1.0.10.dist-info/RECORD
