Metadata-Version: 2.4
Name: device_kit
Version: 1.0.10
Summary: Flow device economical optimization modeling kit
Author-email: Sam Pinkus <sgpinkus@gmail.com>
Maintainer-email: Sam Pinkus <sgpinkus@gmail.com>
Project-URL: Homepage, https://github.com/sgpinkus/device_kit
Project-URL: Issues, https://github.com/sgpinkus/device_kit/issues
Keywords: microgrid,day-ahead,simulation,modeling
Classifier: Programming Language :: Python :: 3
Classifier: License :: OSI Approved :: MIT License
Classifier: Operating System :: OS Independent
Requires-Python: >=3.9.2
Requires-Dist: numpy>=1.26
Requires-Dist: scipy==1.15
Requires-Dist: numdifftools==0.9.41
Provides-Extra: gui
Requires-Dist: PyQt5; extra == "gui"
Provides-Extra: run
Requires-Dist: matplotlib>=3.5; extra == "run"
Requires-Dist: pandas>=2.2; extra == "run"
